{
  "resourceType" : "ValueSet",
  "id" : "ed5a7cf6-0e8b-4c4a-8892-fbdd874fcf3c-527",
  "url" : "http://hl7.org/fhir/comparison/ValueSet/ed5a7cf6-0e8b-4c4a-8892-fbdd874fcf3c-527",
  "name" : "UnionHIVDDE461AndHIVDDE461",
  "title" : "Union of Medications dispensed ValueSet And Medications dispensed ValueSet",
  "status" : "active",
  "date" : "2025-07-24T19:32:16+00:00",
  "compose" : {
    "include" : [{
      "concept" : [{
        "code" : "HIV.D.DE462",
        "display" : "Number of days of medications dispensed"
      },
      {
        "code" : "HIV.D.DE463",
        "display" : "Dosage"
      },
      {
        "code" : "HIV.D.DE464",
        "display" : "Frequency"
      }]
    }]
  }
}